bioquik/__init__.py
bioquik/cli.py
bioquik/fasta_worker.py
bioquik/fmindex.py
bioquik/motifs.py
bioquik/plotter.py
bioquik/processor.py
bioquik/reports.py
bioquik/validate.py
bioquik/wavelettree.py
bioquik-0.1.1.dist-info/METADATA
bioquik-0.1.1.dist-info/WHEEL
bioquik-0.1.1.dist-info/entry_points.txt
bioquik-0.1.1.dist-info/licenses/LICENSE
bioquik-0.1.1.dist-info/RECORD
