Metadata-Version: 2.4
Name: bioquik
Version: 0.1.1
Summary: bioquik is a fast and extensible command-line toolkit for counting CG-anchored DNA motifs in FASTA files. Designed to accelerate bioinformatics pipelines with a simple and parallel interface.
Project-URL: Source, https://github.com/Rajkanwars15/bioquik
Project-URL: Documentation, https://github.com/Rajkanwars15/bioquik#readme
Project-URL: Issue Tracker, https://github.com/Rajkanwars15/bioquik/issues
Author-email: Rajkanwar Singh <rajkanwars15@outlook.com>
License: MIT License
License-File: LICENSE
Keywords: bioinformatics,fast,fm-index,kmer
Classifier: Development Status :: 5 - Production/Stable
Classifier: License :: OSI Approved :: MIT License
Classifier: Operating System :: OS Independent
Classifier: Programming Language :: Python :: 3
Classifier: Programming Language :: Python :: 3 :: Only
Classifier: Programming Language :: Python :: 3.9
Classifier: Programming Language :: Python :: 3.10
Classifier: Programming Language :: Python :: 3.11
Classifier: Programming Language :: Python :: 3.12
Requires-Python: >=3.9
Requires-Dist: pandas>=2.2
Requires-Dist: pydivsufsort>=0.0.18
Requires-Dist: rich>=13.7
Requires-Dist: tqdm>=4.66
Requires-Dist: typer[all]>=0.12
Provides-Extra: dev
Requires-Dist: furo>=2024.1.29; extra == 'dev'
Requires-Dist: matplotlib>=3.10.3; extra == 'dev'
Requires-Dist: myst-parser[linkify]>=2.0; extra == 'dev'
Requires-Dist: pre-commit; extra == 'dev'
Requires-Dist: pytest-cov; extra == 'dev'
Requires-Dist: pytest>=8.2; extra == 'dev'
Requires-Dist: ruff; extra == 'dev'
Requires-Dist: sphinx-autodoc-typehints; extra == 'dev'
Requires-Dist: sphinx-copybutton; extra == 'dev'
Requires-Dist: sphinx>=7.0; extra == 'dev'
Provides-Extra: docs
Requires-Dist: myst-parser[linkify]>=4.0.1; extra == 'docs'
Requires-Dist: sphinx-rtd-theme>=2.0; extra == 'docs'
Requires-Dist: sphinx>=7.3; extra == 'docs'
Provides-Extra: viz
Requires-Dist: matplotlib>=3.10.3; extra == 'viz'
